reflex_chakra/__init__.py
reflex_chakra/constants.py
reflex_chakra/assets/chakra_color_mode_provider.js
reflex_chakra/components/__init__.py
reflex_chakra/components/base.py
reflex_chakra/components/base.pyi
reflex_chakra/components/datadisplay/__init__.py
reflex_chakra/components/datadisplay/badge.py
reflex_chakra/components/datadisplay/badge.pyi
reflex_chakra/components/datadisplay/code.py
reflex_chakra/components/datadisplay/code.pyi
reflex_chakra/components/datadisplay/divider.py
reflex_chakra/components/datadisplay/divider.pyi
reflex_chakra/components/datadisplay/keyboard_key.py
reflex_chakra/components/datadisplay/keyboard_key.pyi
reflex_chakra/components/datadisplay/list.py
reflex_chakra/components/datadisplay/list.pyi
reflex_chakra/components/datadisplay/stat.py
reflex_chakra/components/datadisplay/stat.pyi
reflex_chakra/components/datadisplay/table.py
reflex_chakra/components/datadisplay/table.pyi
reflex_chakra/components/datadisplay/tag.py
reflex_chakra/components/datadisplay/tag.pyi
reflex_chakra/components/disclosure/__init__.py
reflex_chakra/components/disclosure/accordion.py
reflex_chakra/components/disclosure/accordion.pyi
reflex_chakra/components/disclosure/tabs.py
reflex_chakra/components/disclosure/tabs.pyi
reflex_chakra/components/disclosure/transition.py
reflex_chakra/components/disclosure/transition.pyi
reflex_chakra/components/disclosure/visuallyhidden.py
reflex_chakra/components/disclosure/visuallyhidden.pyi
reflex_chakra/components/feedback/__init__.py
reflex_chakra/components/feedback/alert.py
reflex_chakra/components/feedback/alert.pyi
reflex_chakra/components/feedback/circularprogress.py
reflex_chakra/components/feedback/circularprogress.pyi
reflex_chakra/components/feedback/progress.py
reflex_chakra/components/feedback/progress.pyi
reflex_chakra/components/feedback/skeleton.py
reflex_chakra/components/feedback/skeleton.pyi
reflex_chakra/components/feedback/spinner.py
reflex_chakra/components/feedback/spinner.pyi
reflex_chakra-0.8.2.post1.dist-info/METADATA
reflex_chakra-0.8.2.post1.dist-info/WHEEL
reflex_chakra-0.8.2.post1.dist-info/licenses/LICENSE.txt
reflex_chakra-0.8.2.post1.dist-info/RECORD
