Metadata-Version: 2.4
Name: reflex-chakra
Version: 0.8.2.post1
Summary: reflex using chakra components
Author-email: Elijah Ahianyo <elijahahianyo@gmail.com>
Maintainer-email: Khaleel Al-Adhami <khaleel@reflex.dev>, Masen Furer <masen@reflex.dev>, Thomas Brandeho <thomas@reflex.dev>
License: Apache-2.0
License-File: LICENSE.txt
Requires-Python: >=3.10
Requires-Dist: reflex>=0.8.0dev
